Metadata-Version: 1.0
Name: basic-queuetools
Version: 0.1.2
Summary: QueueTools are some special functions to help with software developing
Home-page: http://gitlab.csn.uchile.cl/dpineda/queuetools
Author: David Pineda Osorio
Author-email: dpineda@csn.uchile.cl
License: GPLv3
Platform: UNKNOWN
